socialtelligence/__init__.py
socialtelligence/candidatepipe/__init__.py
socialtelligence/candidatepipe/database.py
socialtelligence/hicandidate/__init__.py
socialtelligence/hicandidate/database.py
socialtelligence/hicandidate/platforms.py
socialtelligence-0.1.2.dist-info/LICENSE
socialtelligence-0.1.2.dist-info/METADATA
socialtelligence-0.1.2.dist-info/WHEEL
socialtelligence-0.1.2.dist-info/top_level.txt
socialtelligence-0.1.2.dist-info/RECORD
