Metadata-Version: 2.1
Name: socialtelligence
Version: 0.1.2
Summary: No description
Home-page: https://www.socialtelligence.io
Author: Willi Schmidt
Author-email: ws.willi.schmidt@gmail.com
Classifier: Programming Language :: Python :: 3
Classifier: License :: OSI Approved :: MIT License
Classifier: Operating System :: OS Independent
Requires-Python: >=3.6
License-File: LICENSE
